sbfi_knime_utils/__init__.py
sbfi_knime_utils/chrome_utils.py
sbfi_knime_utils/file_utils.py
sbfi_knime_utils/logger.py
sbfi_knime_utils-1.4.2.dist-info/METADATA
sbfi_knime_utils-1.4.2.dist-info/WHEEL
sbfi_knime_utils-1.4.2.dist-info/licenses/LICENSE
sbfi_knime_utils-1.4.2.dist-info/RECORD
