Metadata-Version: 2.4
Name: sbfi_knime_utils
Version: 1.4.2
Summary: A lightweight logging utility with folder clearing, browser download support, and pandas DataFrame output.
Project-URL: Homepage, https://github.com/TuiTenTuan/sbfi-knime-utils
Project-URL: Repository, https://github.com/TuiTenTuan/sbfi-knime-utils
Author-email: SBFI CoE Team <sbfap_autobot@suntory.com>
License-File: LICENSE
Keywords: browser,folder,logging,selenium
Classifier: License :: OSI Approved :: MIT License
Classifier: Operating System :: OS Independent
Classifier: Programming Language :: Python :: 3
Requires-Python: >=3.8
Requires-Dist: pandas>=1.5.0
Requires-Dist: selenium>=4.0.0
Requires-Dist: webdriver-manager>=4.0.0
